dumpy/__init__.py
dumpy/optimizers.py
dumpy/train.py
dumpy/utils.py
ywxb/__init__.py
ywxb/optimizers.py
ywxb/train.py
ywxb/utils.py
ywxb-0.0.1.dist-info/METADATA
ywxb-0.0.1.dist-info/WHEEL
ywxb-0.0.1.dist-info/top_level.txt
ywxb-0.0.1.dist-info/RECORD
