Metadata-Version: 2.1
Name: ywxb
Version: 0.0.1
Summary: Neural Network using only numpy
Home-page: UNKNOWN
Author: Maunish Dave
Author-email: maunish1009@gmail.com
License: UNKNOWN
Keywords: python,numpy
Platform: UNKNOWN
Requires-Dist: numpy
